main.py
tests/test_timepix.py
timepix/__init__.py
timepix/core.py
timepix/exceptions.py
timepix-0.1.1.dist-info/licenses/LICENSE
timepix-0.1.1.dist-info/METADATA
timepix-0.1.1.dist-info/WHEEL
timepix-0.1.1.dist-info/top_level.txt
timepix-0.1.1.dist-info/RECORD
